Workbook

Sheet WFP Raw Prices
A1: Date | B1: Admin 1 | C1: Admin 2 | D1: Market | E1: Commodity | F1: Unit | G1: Price (KES) | H1: Price Type | I1: Price Flag | J1: Currency | K1: Source
A2: 45580 | B2: Eastern | C2: Makueni | D2: Kathonzweni (Makueni) | E2: Kale | F2: 50 KG | G2: 1750 | H2: Wholesale | I2: actual | J2: KES | K2: WFP / HDX
A3: 45580 | B3: Nairobi | C3: Nairobi | D3: Wakulima (Nairobi) | E3: Kale | F3: 50 KG | G3: 1500 | H3: Wholesale | I3: actual | J3: KES | K3: WFP / HDX
A4: 45611 | B4: Eastern | C4: Makueni | D4: Kathonzweni (Makueni) | E4: Kale | F4: 50 KG | G4: 1833.5 | H4: Wholesale | I4: actual | J4: KES | K4: WFP / HDX
A5: 45641 | B5: Coast | C5: Kilifi | D5: Dzikunze | E5: Sugar | F5: KG | G5: 150 | H5: Retail | I5: actual | J5: KES | K5: WFP / HDX
A6: 45641 | B6: Coast | C6: Kilifi | D6: Kachororoni | E6: Sugar | F6: KG | G6: 160 | H6: Retail | I6: actual | J6: KES | K6: WFP / HDX
A7: 45641 | B7: Coast | C7: Kilifi | D7: Kaembeni | E7: Sugar | F7: KG | G7: 163 | H7: Retail | I7: actual | J7: KES | K7: WFP / HDX
A8: 45641 | B8: Coast | C8: Tana River | D8: Bangale | E8: Sugar | F8: KG | G8: 149 | H8: Retail | I8: actual | J8: KES | K8: WFP / HDX
A9: 45641 | B9: Coast | C9: Tana River | D9: Bilbil | E9: Sugar | F9: KG | G9: 155 | H9: Retail | I9: actual | J9: KES | K9: WFP / HDX
A10: 45641 | B10: Coast | C10: Tana River | D10: Boka | E10: Sugar | F10: KG | G10: 151 | H10: Retail | I10: actual | J10: KES | K10: WFP / HDX
A11: 45641 | B11: Coast | C11: Tana River | D11: Bura | E11: Sugar | F11: KG | G11: 157.5 | H11: Retail | I11: actual | J11: KES | K11: WFP / HDX
A12: 45641 | B12: Coast | C12: Tana River | D12: Bura | E12: Kale | F12: KG | G12: 67 | H12: Retail | I12: actual | J12: KES | K12: WFP / HDX
A13: 45641 | B13: Coast | C13: Tana River | D13: Charidende | E13: Sugar | F13: KG | G13: 149 | H13: Retail | I13: actual | J13: KES | K13: WFP / HDX
... A1690: 46280 | B1690: Rift Valley | C1690: Turkana | D1690: Mogadishu (Kakuma) | E1690: Beans (dry) | F1690: KG | G1690: 133.33 | H1690: Retail | I1690: aggregate | J1690: KES | K1690: WFP / HDX

Sheet Market Price Snapshot
A1: Lookup Key | B1: Market | C1: Commodity | D1: Unit | E1: Latest Price | F1: Currency | G1: Observation Date
A2: IFO (Daadab)|Maize flour | B2: IFO (Daadab) | C2: Maize flour | D2: KG | E2: 100 | F2: KES | G2: 46280
A3: IFO (Daadab)|Beans (dry) | B3: IFO (Daadab) | C3: Beans (dry) | D3: KG | E3: 120 | F3: KES | G3: 46280
A4: IFO (Daadab)|Kale | B4: IFO (Daadab) | C4: Kale | D4: KG | E4: 60 | F4: KES | G4: 46096
A5: IFO (Daadab)|Milk (cow, fresh) | B5: IFO (Daadab) | C5: Milk (cow, fresh) | D5: L | E5: 180 | F5: KES | G5: 46280
A6: IFO (Daadab)|Oil (vegetable) | B6: IFO (Daadab) | C6: Oil (vegetable) | D6: L | E6: 280 | F6: KES | G6: 46280
A7: IFO (Daadab)|Potatoes (Irish) | B7: IFO (Daadab) | C7: Potatoes (Irish) | D7: KG | E7: 64.39 | F7: KES | G7: 46249
A8: IFO (Daadab)|Rice | B8: IFO (Daadab) | C8: Rice | D8: KG | E8: 106.67 | F8: KES | G8: 46280
A9: IFO (Daadab)|Sugar | B9: IFO (Daadab) | C9: Sugar | D9: KG | E9: 120 | F9: KES | G9: 46280
A10: Kakuma 2|Maize flour | B10: Kakuma 2 | C10: Maize flour | D10: KG | E10: 79.63 | F10: KES | G10: 46249
A11: Kakuma 2|Beans (dry) | B11: Kakuma 2 | C11: Beans (dry) | D11: KG | E11: 120 | F11: KES | G11: 46249
A12: Kakuma 2|Kale | B12: Kakuma 2 | C12: Kale | D12: KG | E12: 100 | F12: KES | G12: 46096
A13: Kakuma 2|Oil (vegetable) | B13: Kakuma 2 | C13: Oil (vegetable) | D13: L | E13: 287.04 | F13: KES | G13: 46249
... A16: Kakuma 2|Sugar | B16: Kakuma 2 | C16: Sugar | D16: KG | E16: 152.22 | F16: KES | G16: 46249

Sheet Healthy Basket
A1: FOODWISE | Healthy Basket Calculator
A2: Editable scenario only — quantities are illustrative, not an FAO or clinical diet prescription.
A4: Selected market | B4: IFO (Daadab) | D4: Yellow cells are editable. Prices/units/dates come from the latest matching WFP record in the selected market.
A7: Food item | B7: Quantity / person / week | C7: Recorded unit | D7: Unit price (KES) | E7: Weekly cost (KES) | F7: Latest observation
A8: Maize flour | B8: 1.5 | C8: =IFERROR(VLOOKUP($B$4&"|"&A8,'Market Price Snapshot'!$A$2:$G$16,4,FALSE),"") -> KG | D8: =IFERROR(VLOOKUP($B$4&"|"&A8,'Market Price Snapshot'!$A$2:$G$16,5,FALSE),"") -> 100 | E8: =IF(OR(C8="",D8=""),"",B8*D8) -> 150 | F8: =IFERROR(VLOOKUP($B$4&"|"&A8,'Market Price Snapshot'!$A$2:$G$16,7,FALSE),"") -> 2026-09-15 00:00:00
A9: Beans (dry) | B9: 0.35 | C9: =IFERROR(VLOOKUP($B$4&"|"&A9,'Market Price Snapshot'!$A$2:$G$16,4,FALSE),"") -> KG | D9: =IFERROR(VLOOKUP($B$4&"|"&A9,'Market Price Snapshot'!$A$2:$G$16,5,FALSE),"") -> 120 | E9: =IF(OR(C9="",D9=""),"",B9*D9) -> 42 | F9: =IFERROR(VLOOKUP($B$4&"|"&A9,'Market Price Snapshot'!$A$2:$G$16,7,FALSE),"") -> 2026-09-15 00:00:00
A10: Kale | B10: 0.75 | C10: =IFERROR(VLOOKUP($B$4&"|"&A10,'Market Price Snapshot'!$A$2:$G$16,4,FALSE),"") -> KG | D10: =IFERROR(VLOOKUP($B$4&"|"&A10,'Market Price Snapshot'!$A$2:$G$16,5,FALSE),"") -> 60 | E10: =IF(OR(C10="",D10=""),"",B10*D10) -> 45 | F10: =IFERROR(VLOOKUP($B$4&"|"&A10,'Market Price Snapshot'!$A$2:$G$16,7,FALSE),"") -> 2026-03-15 00:00:00
A11: Milk (cow, fresh) | B11: 1.75 | C11: =IFERROR(VLOOKUP($B$4&"|"&A11,'Market Price Snapshot'!$A$2:$G$16,4,FALSE),"") -> L | D11: =IFERROR(VLOOKUP($B$4&"|"&A11,'Market Price Snapshot'!$A$2:$G$16,5,FALSE),"") -> 180 | E11: =IF(OR(C11="",D11=""),"",B11*D11) -> 315 | F11: =IFERROR(VLOOKUP($B$4&"|"&A11,'Market Price Snapshot'!$A$2:$G$16,7,FALSE),"") -> 2026-09-15 00:00:00
A12: Oil (vegetable) | B12: 0.25 | C12: =IFERROR(VLOOKUP($B$4&"|"&A12,'Market Price Snapshot'!$A$2:$G$16,4,FALSE),"") -> L | D12: =IFERROR(VLOOKUP($B$4&"|"&A12,'Market Price Snapshot'!$A$2:$G$16,5,FALSE),"") -> 280 | E12: =IF(OR(C12="",D12=""),"",B12*D12) -> 70 | F12: =IFERROR(VLOOKUP($B$4&"|"&A12,'Market Price Snapshot'!$A$2:$G$16,7,FALSE),"") -> 2026-09-15 00:00:00
A13: Potatoes (Irish) | B13: 0.75 | C13: =IFERROR(VLOOKUP($B$4&"|"&A13,'Market Price Snapshot'!$A$2:$G$16,4,FALSE),"") -> KG | D13: =IFERROR(VLOOKUP($B$4&"|"&A13,'Market Price Snapshot'!$A$2:$G$16,5,FALSE),"") -> 64.39 | E13: =IF(OR(C13="",D13=""),"",B13*D13) -> 48.2925 | F13: =IFERROR(VLOOKUP($B$4&"|"&A13,'Market Price Snapshot'!$A$2:$G$16,7,FALSE),"") -> 2026-08-15 00:00:00
A14: Rice | B14: 0.35 | C14: =IFERROR(VLOOKUP($B$4&"|"&A14,'Market Price Snapshot'!$A$2:$G$16,4,FALSE),"") -> KG | D14: =IFERROR(VLOOKUP($B$4&"|"&A14,'Market Price Snapshot'!$A$2:$G$16,5,FALSE),"") -> 106.67 | E14: =IF(OR(C14="",D14=""),"",B14*D14) -> 37.3345 | F14: =IFERROR(VLOOKUP($B$4&"|"&A14,'Market Price Snapshot'!$A$2:$G$16,7,FALSE),"") -> 2026-09-15 00:00:00
A17: Weekly total for priced foods | E17: =SUM(E8:E14) -> 707.627
A18: Price coverage | E18: =COUNT(D8:D14)&" / 7 items" -> 7 / 7 items
A20: Interpretation: the total is the sum of only the listed foods with available prices. The chosen weekly quantities are demonstration assumptions. Confirm comparable units, quality, prices and a nutritionist-approved basket before presenting this as a diet cost.

Sheet Household Simulator
A1: FOODWISE | Household Pressure Simulator
A2: Uses the currently selected market and only the foods with recorded prices.
A4: Household size (people) | B4: 4
A5: Monthly household income (KES) | B5: 25000
A7: Selected market | B7: ='Healthy Basket'!B4 -> IFO (Daadab)
A8: Priced foods available | B8: =COUNT('Healthy Basket'!D8:D14) -> 7
A9: Weekly cost per person (priced foods) | B9: ='Healthy Basket'!E17 -> 707.627
A10: Monthly cost per person (KES) | B10: =B9*4.345 -> 3074.6393
A11: Monthly household cost (KES) | B11: =B10*B4 -> 12298.557
A12: Income share for priced foods | B12: =IF(B5>0,B11/B5,"") -> 0.49194229
A13: Affordability score (0-100) | B13: =IF(B5>0,MAX(0,MIN(100,100-B12*100)),"") -> 50.805771
A14: Pressure signal | B14: =IF(B12>60%,"Critical: above 60%",IF(B12>=50%,"Watch: 50–60%","Below prototype thresholds")) -> Below prototype thresholds
A15: Data coverage warning | B15: =IF(B8<7,"PARTIAL: missing prices; cost is understated","All listed food prices available") -> All listed food prices available
A18: Score definition: max(0, 100 − income share in percentage points). The 50%/60% warning thresholds and score are prototype signals, not validated poverty, nutrition or clinical thresholds. A partial basket can only understate pressure.

Sheet Dashboard & Charts
A1: FOODWISE | Kenya Food Price Intelligence
A2: Monthly median of reported WFP market observations; exact commodity and most common unit shown. Not county-weighted and not a KNBS CPI series.
A3: Selected records: 1,689 from 2024-10-01 to 2026-09-15; 139 distinct markets.
A38: Month | B38: Commodity | C38: Unit | D38: Median KES | E38: Market observations
A39: 45566 | B39: Maize flour | C39: KG | D39: 76.67 | E39: 11
A40: 45597 | B40: Maize flour | C40: KG | D40: 80 | E40: 11
A41: 45627 | B41: Maize flour | C41: KG | D41: 78.855 | E41: 12
A42: 45658 | B42: Maize flour | C42: KG | D42: 81.665 | E42: 8
A43: 45689 | B43: Maize flour | C43: KG | D43: 80 | E43: 12
A44: 45717 | B44: Maize flour | C44: KG | D44: 80 | E44: 11
A45: 45748 | B45: Maize flour | C45: KG | D45: 80 | E45: 3
A46: 45778 | B46: Maize flour | C46: KG | D46: 90 | E46: 7
A47: 45809 | B47: Maize flour | C47: KG | D47: 90 | E47: 12
A48: 45839 | B48: Maize flour | C48: KG | D48: 90 | E48: 9
A49: 45870 | B49: Maize flour | C49: KG | D49: 83.33 | E49: 11
A50: 45901 | B50: Maize flour | C50: KG | D50: 83.33 | E50: 10
... A134: 46266 | B134: Rice | C134: KG | D134: 125 | E134: 4

Sheet Read Me & Notes
A1: FOODWISE | Read Me & Data Notes
A3: Data and freshness
A4: Official WFP Kenya food-price file downloaded from HDX on 8 October 2026. The full source file contains 27,897 rows through 2026-09-15; the workbook's raw tab contains 1,689 selected food observations from October 2024 onward. Latest file metadata update reported by HDX: 4 October 2026.
A7: WFP Kenya Food Prices (HDX)
A8: KNBS September 2026 CPI release
A10: Use these supplied benchmarks carefully
A11: Brief-supplied figures: 43.5–43.9 million people (about 76–77%) unable to afford a healthy diet; estimated daily healthy-diet cost KSh 189–582 depending on method; September 2026 food and non-alcoholic beverages inflation 9.5% (verified on the KNBS release page). The million/percentage and cost range need their precise FAO edition, year, geographic definition and method attached before external publication.
A15: Important limits
A16: WFP observations are not a nationally representative retail panel; markets and dates vary. The most recent multi-item records in this extract include IFO (Daadab) and Kakuma 2; these are camp markets, not a proxy for Nairobi or Nyeri households. The market dropdown intentionally shows only markets with multiple recent target-item records. Units are kept as published, prices may be missing/stale, and the simulator flags incomplete coverage. Food quantities are editable demo inputs, not a recommended healthy diet. The score and 50%/60% flags are concept-stage indicators, not validated policy thresholds. Diet-gap module requires an agreed healthy-diet basket and nutrient data.
A23: Formula conventions
A24: Monthly cost = weekly basket cost × 4.345 weeks/month × household size. Income share = monthly household cost ÷ monthly household income. Affordability score = max(0, 100 − income share in percentage points). If one or more prices are missing, totals include only priced foods and the household cost is an underestimate.
